jupyter_save_load_vars.py
jupyter_save_load_vars-0.3.0.dist-info/LICENSE
jupyter_save_load_vars-0.3.0.dist-info/METADATA
jupyter_save_load_vars-0.3.0.dist-info/WHEEL
jupyter_save_load_vars-0.3.0.dist-info/top_level.txt
jupyter_save_load_vars-0.3.0.dist-info/RECORD
