Metadata-Version: 2.1
Name: jupyter-save-load-vars
Version: 0.3.0
Summary: Saves and loads variables to/from a IPython/Jupyter workspac
Author-email: Tobi Delbruck <tobidelbruck@gmail.com>
Project-URL: Homepage, https://github.com/tobidelbruck/saveloadvars
Project-URL: Bug Tracker, https://github.com/tobidelbruck/saveloadvars/issues
Project-URL: Change Log, https://github.com/tobidelbruck/saveloadvar/CHANGELOG.md
Classifier: Programming Language :: Python :: 3
Classifier: License :: OSI Approved :: MIT License
Classifier: Operating System :: OS Independent
Requires-Python: >=3.8
License-File: LICENSE
Requires-Dist: dill >=0.3.7
Provides-Extra: dev
Requires-Dist: flake8 ; extra == 'dev'
Requires-Dist: pytest ; extra == 'dev'
